ufc_fighter_paul-0.2.1.dist-info/METADATA
ufc_fighter_paul-0.2.1.dist-info/WHEEL
ufc_fighter_paul/__init__.py
ufc_fighter_paul/lastdance.py
ufc_fighter_paul-0.2.1.dist-info/RECORD
