Metadata-Version: 2.1
Name: ufc-fighter-paul
Version: 0.2.1
Summary: In commemoration of paul's last dance
Author-Email: pppaal <pjyrhee@gmail.com>
License: MIT
Requires-Python: >=3.9
